pylabtools/__init__.py
pylabtools/file_wrapper.py
pylabtools/log_wrapper.py
pylabtools/minio_wrapper.py
pylabtools/path_wrapper.py
tests/__init__.py
tests/test_file_wrapper.py
tests/test_log_wrapper.py
tests/test_path_wrapper.py
pylabtools-2.0.0.dist-info/METADATA
pylabtools-2.0.0.dist-info/WHEEL
pylabtools-2.0.0.dist-info/top_level.txt
pylabtools-2.0.0.dist-info/RECORD
