Metadata-Version: 2.1
Name: pylabtools
Version: 2.0.0
Summary: python utility for research
Home-page: https://github.com/tinnawong/pylabtools
Author: Tinnawong saelao
Author-email: tinnawong2010@hotmail.com
Classifier: Programming Language :: Python :: 3
Classifier: Operating System :: OS Independent
Requires-Dist: minio ==7.1.15
Requires-Dist: tqdm ==4.64.1
